{"insertId":"ivc9cdfvadr4v","jsonPayload":{"actor":{"user":"nobody@redhat.com"},"event_subtype":"compute.instances.stop","event_timestamp_us":"1526909800472279","event_type":"GCE_OPERATION_DONE","operation":{"id":"7767268896145372628","name":"operation-1526909755175-56cb7618fb059-791844b8-32ecf774","type":"operation","zone":"us-east1-b"},"resource":{"id":"1925828475519697814","name":"debian-1","type":"instance","zone":"us-east1-b"},"trace_id":"operation-1526909755175-56cb7618fb059-791844b8-32ecf774","version":"1.2"},"labels":{"compute.googleapis.com/resource_id":"1925828475519697814","compute.googleapis.com/resource_name":"debian-1","compute.googleapis.com/resource_type":"instance","compute.googleapis.com/resource_zone":"us-east1-b"},"logName":"projects/GOOGLE_PROJECT/logs/compute.googleapis.com%2Factivity_log","receiveTimestamp":"2018-05-21T13:36:40.578908564Z","resource":{"labels":{"instance_id":"1925828475519697814","project_id":"GOOGLE_PROJECT","zone":"us-east1-b"},"type":"gce_instance"},"severity":"INFO","timestamp":"2018-05-21T13:36:40.472279Z"}
